calibration.py
calibration_belt-0.1.3.dist-info/LICENSE
calibration_belt-0.1.3.dist-info/METADATA
calibration_belt-0.1.3.dist-info/WHEEL
calibration_belt-0.1.3.dist-info/top_level.txt
calibration_belt-0.1.3.dist-info/RECORD
