Metadata-Version: 2.1
Name: calibration-belt
Version: 0.1.3
Summary: Assessment of calibration in binomial prediction models.
Home-page: https://github.com/lbulgarelli/calibration
Author: Lucas Bulgarelli
Author-email: lucas1@mit.edu
License: MIT
Keywords: calibration calibration-belt p-value goodness-of-fit
Platform: UNKNOWN
Requires-Dist: numpy (>=1.19.1)
Requires-Dist: tqdm (>=4.48.2)
Requires-Dist: matplotlib (>=3.3.0)
Requires-Dist: scipy (>=1.5.2)
Requires-Dist: statsmodels (>=0.11.1)
